Workbook

Sheet Dashboard
A1: EXCEL BUSINESS MANAGEMENT SYSTEM — V2
A3: V3 • Professional Data Entry • Invoice • Receipt • PDF Workflow
A5: TOTAL SALES | C5: TOTAL PURCHASES | E5: NET PROFIT | G5: RECEIVABLES | I5: PAYABLES | K5: INVENTORY VALUE
A6: =Reports!B2 | C6: =Reports!B3 | E6: =Reports!B6 | G6: =Reports!B7 | I6: =Reports!B8 | K6: =Reports!B9
A8: CUSTOMERS | C8: PRODUCTS | E8: LOW STOCK | G8: PAID SALES | I8: PENDING SALES | K8: PARTIAL SALES
A9: =Reports!B10 | C9: =Reports!B11 | E9: =Reports!B12 | G9: =COUNTIF(Sales[PaymentStatus],"Paid") | I9: =COUNTIF(Sales[PaymentStatus],"Pending") | K9: =COUNTIF(Sales[PaymentStatus],"Partial")
A28: RECEIVABLES & PAYABLES SUMMARY | G28: LOW STOCK ALERT
A29: Customer Receivable | B29: Supplier Payable | C29: Net Position | D29: Pending Sales | E29: Pending Purchases | F29: Inventory Value | G29: Product | H29: Current Stock | I29: Reorder Level | J29: Status
A30: =Reports!B7 | B30: =Reports!B8 | C30: =A30-B30 | D30: =COUNTIF(Sales[PaymentStatus],"Pending") | E30: =COUNTIF(Purchases[PaymentStatus],"Pending") | F30: =Reports!B9 | G30: =IFERROR(FILTER(Products[ProductName],Products[StockStatus]="LOW"),"No low-stock items")
A34: DATA ENTRY & DOCUMENT CENTER
A36: NEW CUSTOMER | D36: NEW PRODUCT | G36: NEW SALE | J36: NEW PURCHASE
A39: NEW EXPENSE | D39: RECEIVE PAYMENT | G39: INVOICE | J39: RECEIPT

Sheet DataEntry
A1: PROFESSIONAL DATA ENTRY CENTER — V3
A4: Quick Actions
A6: NEW CUSTOMER | C6: NEW PRODUCT | E6: NEW SALE | G6: NEW PURCHASE
A9: NEW EXPENSE | C9: RECEIVE PAYMENT | E9: INVOICE | G9: RECEIPT
A13: V3 Workflow
A14: 1. Enter/select master data
A15: 2. Record transaction
A16: 3. Save into database table
A17: 4. Generate invoice / receipt
A18: 5. Export document to PDF
A19: 6. Refresh dashboard and reports
A22: VBA Automation Layer
A23: The UI is prepared. VBA will add real buttons, validation, save/clear logic, document generation and PDF export.

Sheet Customers
A1: CustomerID | B1: CustomerName | C1: Mobile | D1: Email | E1: Address | F1: GSTIN | G1: OpeningBalance | H1: CreditLimit | I1: Status
A2: C001 | B2: Sample Customer | G2: 0 | H2: 50000 | I2: Active

Sheet Products
A1: ProductID | B1: ProductName | C1: Category | D1: Unit | E1: PurchasePrice | F1: SalePrice | G1: OpeningStock | H1: ReorderLevel | I1: PurchasedQty | J1: SoldQty | K1: CurrentStock | L1: StockValue | M1: StockStatus | N1: Status
A2: P001 | B2: Sample Product | C2: General | D2: Nos | E2: 100 | F2: 150 | G2: 100 | H2: 10 | I2: =IF(A2="","",SUMIFS(Purchases[Quantity],Purchases[ProductID],A2)) | J2: =IF(A2="","",SUMIFS(Sales[Quantity],Sales[ProductID],A2)) | K2: =IF(A2="","",N(G2)+N(I2)-N(J2)) | L2: =IF(K2="","",K2*N(F2)) | M2: =IF(K2="","",IF(K2<=N(H2),"LOW","OK")) | N2: Active
I3: =IF(A3="","",SUMIFS(Purchases[Quantity],Purchases[ProductID],A3)) | J3: =IF(A3="","",SUMIFS(Sales[Quantity],Sales[ProductID],A3)) | K3: =IF(A3="","",N(G3)+N(I3)-N(J3)) | L3: =IF(K3="","",K3*N(F3)) | M3: =IF(K3="","",IF(K3<=N(H3),"LOW","OK"))
I4: =IF(A4="","",SUMIFS(Purchases[Quantity],Purchases[ProductID],A4)) | J4: =IF(A4="","",SUMIFS(Sales[Quantity],Sales[ProductID],A4)) | K4: =IF(A4="","",N(G4)+N(I4)-N(J4)) | L4: =IF(K4="","",K4*N(F4)) | M4: =IF(K4="","",IF(K4<=N(H4),"LOW","OK"))
I5: =IF(A5="","",SUMIFS(Purchases[Quantity],Purchases[ProductID],A5)) | J5: =IF(A5="","",SUMIFS(Sales[Quantity],Sales[ProductID],A5)) | K5: =IF(A5="","",N(G5)+N(I5)-N(J5)) | L5: =IF(K5="","",K5*N(F5)) | M5: =IF(K5="","",IF(K5<=N(H5),"LOW","OK"))
I6: =IF(A6="","",SUMIFS(Purchases[Quantity],Purchases[ProductID],A6)) | J6: =IF(A6="","",SUMIFS(Sales[Quantity],Sales[ProductID],A6)) | K6: =IF(A6="","",N(G6)+N(I6)-N(J6)) | L6: =IF(K6="","",K6*N(F6)) | M6: =IF(K6="","",IF(K6<=N(H6),"LOW","OK"))
I7: =IF(A7="","",SUMIFS(Purchases[Quantity],Purchases[ProductID],A7)) | J7: =IF(A7="","",SUMIFS(Sales[Quantity],Sales[ProductID],A7)) | K7: =IF(A7="","",N(G7)+N(I7)-N(J7)) | L7: =IF(K7="","",K7*N(F7)) | M7: =IF(K7="","",IF(K7<=N(H7),"LOW","OK"))
I8: =IF(A8="","",SUMIFS(Purchases[Quantity],Purchases[ProductID],A8)) | J8: =IF(A8="","",SUMIFS(Sales[Quantity],Sales[ProductID],A8)) | K8: =IF(A8="","",N(G8)+N(I8)-N(J8)) | L8: =IF(K8="","",K8*N(F8)) | M8: =IF(K8="","",IF(K8<=N(H8),"LOW","OK"))
I9: =IF(A9="","",SUMIFS(Purchases[Quantity],Purchases[ProductID],A9)) | J9: =IF(A9="","",SUMIFS(Sales[Quantity],Sales[ProductID],A9)) | K9: =IF(A9="","",N(G9)+N(I9)-N(J9)) | L9: =IF(K9="","",K9*N(F9)) | M9: =IF(K9="","",IF(K9<=N(H9),"LOW","OK"))
I10: =IF(A10="","",SUMIFS(Purchases[Quantity],Purchases[ProductID],A10)) | J10: =IF(A10="","",SUMIFS(Sales[Quantity],Sales[ProductID],A10)) | K10: =IF(A10="","",N(G10)+N(I10)-N(J10)) | L10: =IF(K10="","",K10*N(F10)) | M10: =IF(K10="","",IF(K10<=N(H10),"LOW","OK"))
I11: =IF(A11="","",SUMIFS(Purchases[Quantity],Purchases[ProductID],A11)) | J11: =IF(A11="","",SUMIFS(Sales[Quantity],Sales[ProductID],A11)) | K11: =IF(A11="","",N(G11)+N(I11)-N(J11)) | L11: =IF(K11="","",K11*N(F11)) | M11: =IF(K11="","",IF(K11<=N(H11),"LOW","OK"))
I12: =IF(A12="","",SUMIFS(Purchases[Quantity],Purchases[ProductID],A12)) | J12: =IF(A12="","",SUMIFS(Sales[Quantity],Sales[ProductID],A12)) | K12: =IF(A12="","",N(G12)+N(I12)-N(J12)) | L12: =IF(K12="","",K12*N(F12)) | M12: =IF(K12="","",IF(K12<=N(H12),"LOW","OK"))
I13: =IF(A13="","",SUMIFS(Purchases[Quantity],Purchases[ProductID],A13)) | J13: =IF(A13="","",SUMIFS(Sales[Quantity],Sales[ProductID],A13)) | K13: =IF(A13="","",N(G13)+N(I13)-N(J13)) | L13: =IF(K13="","",K13*N(F13)) | M13: =IF(K13="","",IF(K13<=N(H13),"LOW","OK"))
I14: =IF(A14="","",SUMIFS(Purchases[Quantity],Purchases[ProductID],A14)) | J14: =IF(A14="","",SUMIFS(Sales[Quantity],Sales[ProductID],A14)) | K14: =IF(A14="","",N(G14)+N(I14)-N(J14)) | L14: =IF(K14="","",K14*N(F14)) | M14: =IF(K14="","",IF(K14<=N(H14),"LOW","OK"))
... I1000: =IF(A1000="","",SUMIFS(Purchases[Quantity],Purchases[ProductID],A1000)) | J1000: =IF(A1000="","",SUMIFS(Sales[Quantity],Sales[ProductID],A1000)) | K1000: =IF(A1000="","",N(G1000)+N(I1000)-N(J1000)) | L1000: =IF(K1000="","",K1000*N(F1000)) | M1000: =IF(K1000="","",IF(K1000<=N(H1000),"LOW","OK"))

Sheet Suppliers
A1: SupplierID | B1: SupplierName | C1: Mobile | D1: Email | E1: GSTIN | F1: Address | G1: OpeningBalance | H1: CreditLimit | I1: Status
A2: SUP001 | B2: Sample Supplier | G2: 0 | H2: 50000 | I2: Active

Sheet Employees
A1: EmployeeID | B1: EmployeeName | C1: Department | D1: Mobile | E1: Email | F1: JoiningDate | G1: Salary | H1: Status
A2: E001 | B2: Sample Employee | C2: Administration | F2: 15-08-2026 | G2: 0 | H2: Active

Sheet Sales
A1: SaleID | B1: Date | C1: CustomerID | D1: ProductID | E1: Quantity | F1: Rate | G1: Discount | H1: Tax | I1: NetAmount | J1: PaymentReceived | K1: Balance | L1: PaymentStatus
A2: S001 | B2: 15-08-2026 | C2: C001 | D2: P001 | E2: 2 | F2: 150 | G2: 0 | H2: 0 | I2: =IF(OR(E2="",F2=""),"",E2*F2-N(G2)+N(H2)) | J2: 300 | K2: =IF(I2="","",I2-N(J2)) | L2: =IF(I2="","",IF(K2<=0,"Paid",IF(J2>0,"Partial","Pending")))
I3: =IF(OR(E3="",F3=""),"",E3*F3-N(G3)+N(H3)) | K3: =IF(I3="","",I3-N(J3)) | L3: =IF(I3="","",IF(K3<=0,"Paid",IF(J3>0,"Partial","Pending")))
I4: =IF(OR(E4="",F4=""),"",E4*F4-N(G4)+N(H4)) | K4: =IF(I4="","",I4-N(J4)) | L4: =IF(I4="","",IF(K4<=0,"Paid",IF(J4>0,"Partial","Pending")))
I5: =IF(OR(E5="",F5=""),"",E5*F5-N(G5)+N(H5)) | K5: =IF(I5="","",I5-N(J5)) | L5: =IF(I5="","",IF(K5<=0,"Paid",IF(J5>0,"Partial","Pending")))
I6: =IF(OR(E6="",F6=""),"",E6*F6-N(G6)+N(H6)) | K6: =IF(I6="","",I6-N(J6)) | L6: =IF(I6="","",IF(K6<=0,"Paid",IF(J6>0,"Partial","Pending")))
I7: =IF(OR(E7="",F7=""),"",E7*F7-N(G7)+N(H7)) | K7: =IF(I7="","",I7-N(J7)) | L7: =IF(I7="","",IF(K7<=0,"Paid",IF(J7>0,"Partial","Pending")))
I8: =IF(OR(E8="",F8=""),"",E8*F8-N(G8)+N(H8)) | K8: =IF(I8="","",I8-N(J8)) | L8: =IF(I8="","",IF(K8<=0,"Paid",IF(J8>0,"Partial","Pending")))
I9: =IF(OR(E9="",F9=""),"",E9*F9-N(G9)+N(H9)) | K9: =IF(I9="","",I9-N(J9)) | L9: =IF(I9="","",IF(K9<=0,"Paid",IF(J9>0,"Partial","Pending")))
I10: =IF(OR(E10="",F10=""),"",E10*F10-N(G10)+N(H10)) | K10: =IF(I10="","",I10-N(J10)) | L10: =IF(I10="","",IF(K10<=0,"Paid",IF(J10>0,"Partial","Pending")))
I11: =IF(OR(E11="",F11=""),"",E11*F11-N(G11)+N(H11)) | K11: =IF(I11="","",I11-N(J11)) | L11: =IF(I11="","",IF(K11<=0,"Paid",IF(J11>0,"Partial","Pending")))
I12: =IF(OR(E12="",F12=""),"",E12*F12-N(G12)+N(H12)) | K12: =IF(I12="","",I12-N(J12)) | L12: =IF(I12="","",IF(K12<=0,"Paid",IF(J12>0,"Partial","Pending")))
I13: =IF(OR(E13="",F13=""),"",E13*F13-N(G13)+N(H13)) | K13: =IF(I13="","",I13-N(J13)) | L13: =IF(I13="","",IF(K13<=0,"Paid",IF(J13>0,"Partial","Pending")))
I14: =IF(OR(E14="",F14=""),"",E14*F14-N(G14)+N(H14)) | K14: =IF(I14="","",I14-N(J14)) | L14: =IF(I14="","",IF(K14<=0,"Paid",IF(J14>0,"Partial","Pending")))
... I1000: =IF(OR(E1000="",F1000=""),"",E1000*F1000-N(G1000)+N(H1000)) | K1000: =IF(I1000="","",I1000-N(J1000)) | L1000: =IF(I1000="","",IF(K1000<=0,"Paid",IF(J1000>0,"Partial","Pending")))

Sheet Purchases
A1: PurchaseID | B1: Date | C1: SupplierID | D1: ProductID | E1: Quantity | F1: Rate | G1: Tax | H1: NetAmount | I1: PaymentMade | J1: Balance | K1: PaymentStatus
A2: PUR001 | B2: 15-08-2026 | C2: SUP001 | D2: P001 | E2: 10 | F2: 100 | G2: 0 | H2: =IF(OR(E2="",F2=""),"",E2*F2+N(G2)) | I2: 1000 | J2: =IF(H2="","",H2-N(I2)) | K2: =IF(H2="","",IF(J2<=0,"Paid",IF(I2>0,"Partial","Pending")))
H3: =IF(OR(E3="",F3=""),"",E3*F3+N(G3)) | J3: =IF(H3="","",H3-N(I3)) | K3: =IF(H3="","",IF(J3<=0,"Paid",IF(I3>0,"Partial","Pending")))
H4: =IF(OR(E4="",F4=""),"",E4*F4+N(G4)) | J4: =IF(H4="","",H4-N(I4)) | K4: =IF(H4="","",IF(J4<=0,"Paid",IF(I4>0,"Partial","Pending")))
H5: =IF(OR(E5="",F5=""),"",E5*F5+N(G5)) | J5: =IF(H5="","",H5-N(I5)) | K5: =IF(H5="","",IF(J5<=0,"Paid",IF(I5>0,"Partial","Pending")))
H6: =IF(OR(E6="",F6=""),"",E6*F6+N(G6)) | J6: =IF(H6="","",H6-N(I6)) | K6: =IF(H6="","",IF(J6<=0,"Paid",IF(I6>0,"Partial","Pending")))
H7: =IF(OR(E7="",F7=""),"",E7*F7+N(G7)) | J7: =IF(H7="","",H7-N(I7)) | K7: =IF(H7="","",IF(J7<=0,"Paid",IF(I7>0,"Partial","Pending")))
H8: =IF(OR(E8="",F8=""),"",E8*F8+N(G8)) | J8: =IF(H8="","",H8-N(I8)) | K8: =IF(H8="","",IF(J8<=0,"Paid",IF(I8>0,"Partial","Pending")))
H9: =IF(OR(E9="",F9=""),"",E9*F9+N(G9)) | J9: =IF(H9="","",H9-N(I9)) | K9: =IF(H9="","",IF(J9<=0,"Paid",IF(I9>0,"Partial","Pending")))
H10: =IF(OR(E10="",F10=""),"",E10*F10+N(G10)) | J10: =IF(H10="","",H10-N(I10)) | K10: =IF(H10="","",IF(J10<=0,"Paid",IF(I10>0,"Partial","Pending")))
H11: =IF(OR(E11="",F11=""),"",E11*F11+N(G11)) | J11: =IF(H11="","",H11-N(I11)) | K11: =IF(H11="","",IF(J11<=0,"Paid",IF(I11>0,"Partial","Pending")))
H12: =IF(OR(E12="",F12=""),"",E12*F12+N(G12)) | J12: =IF(H12="","",H12-N(I12)) | K12: =IF(H12="","",IF(J12<=0,"Paid",IF(I12>0,"Partial","Pending")))
H13: =IF(OR(E13="",F13=""),"",E13*F13+N(G13)) | J13: =IF(H13="","",H13-N(I13)) | K13: =IF(H13="","",IF(J13<=0,"Paid",IF(I13>0,"Partial","Pending")))
H14: =IF(OR(E14="",F14=""),"",E14*F14+N(G14)) | J14: =IF(H14="","",H14-N(I14)) | K14: =IF(H14="","",IF(J14<=0,"Paid",IF(I14>0,"Partial","Pending")))
... H1000: =IF(OR(E1000="",F1000=""),"",E1000*F1000+N(G1000)) | J1000: =IF(H1000="","",H1000-N(I1000)) | K1000: =IF(H1000="","",IF(J1000<=0,"Paid",IF(I1000>0,"Partial","Pending")))

Sheet Expenses
A1: ExpenseID | B1: Date | C1: Category | D1: Description | E1: Amount | F1: PaymentMode
A2: EXP001 | B2: 15-08-2026 | C2: Office | D2: Sample expense | E2: 0 | F2: Cash

Sheet Payments
A1: PaymentID | B1: Date | C1: PartyType | D1: PartyID | E1: Reference | F1: Amount | G1: PaymentMode
A2: PAY001 | B2: 15-08-2026 | C2: Customer | D2: C001 | E2: Opening | F2: 0 | G2: Cash

Sheet Reports
A1: REPORT | B1: VALUE
A2: Total Sales | B2: =SUM(Sales[NetAmount])
A3: Total Purchases | B3: =SUM(Purchases[NetAmount])
A4: Total Expenses | B4: =SUM(Expenses[Amount])
A5: Gross Profit | B5: =B2-B3
A6: Net Profit | B6: =B5-B4
A7: Customer Receivables | B7: =SUM(Sales[Balance])
A8: Supplier Payables | B8: =SUM(Purchases[Balance])
A9: Inventory Value | B9: =SUM(Products[StockValue])
A10: Total Customers | B10: =COUNTA(Customers[CustomerID])
A11: Total Products | B11: =COUNTA(Products[ProductID])
A12: Low Stock Items | B12: =COUNTIF(Products[StockStatus],"LOW")
A16: Month | B16: Sales | C16: Purchases | D16: Expenses
A17: Jan | B17: =SUMPRODUCT((MONTH(Sales[Date])=1)*Sales[NetAmount]) | C17: =SUMPRODUCT((MONTH(Purchases[Date])=1)*Purchases[NetAmount]) | D17: =SUMPRODUCT((MONTH(Expenses[Date])=1)*Expenses[Amount])
A18: Feb | B18: =SUMPRODUCT((MONTH(Sales[Date])=2)*Sales[NetAmount]) | C18: =SUMPRODUCT((MONTH(Purchases[Date])=2)*Purchases[NetAmount]) | D18: =SUMPRODUCT((MONTH(Expenses[Date])=2)*Expenses[Amount])
A19: Mar | B19: =SUMPRODUCT((MONTH(Sales[Date])=3)*Sales[NetAmount]) | C19: =SUMPRODUCT((MONTH(Purchases[Date])=3)*Purchases[NetAmount]) | D19: =SUMPRODUCT((MONTH(Expenses[Date])=3)*Expenses[Amount])
A20: Apr | B20: =SUMPRODUCT((MONTH(Sales[Date])=4)*Sales[NetAmount]) | C20: =SUMPRODUCT((MONTH(Purchases[Date])=4)*Purchases[NetAmount]) | D20: =SUMPRODUCT((MONTH(Expenses[Date])=4)*Expenses[Amount])
A21: May | B21: =SUMPRODUCT((MONTH(Sales[Date])=5)*Sales[NetAmount]) | C21: =SUMPRODUCT((MONTH(Purchases[Date])=5)*Purchases[NetAmount]) | D21: =SUMPRODUCT((MONTH(Expenses[Date])=5)*Expenses[Amount])
A22: Jun | B22: =SUMPRODUCT((MONTH(Sales[Date])=6)*Sales[NetAmount]) | C22: =SUMPRODUCT((MONTH(Purchases[Date])=6)*Purchases[NetAmount]) | D22: =SUMPRODUCT((MONTH(Expenses[Date])=6)*Expenses[Amount])
A23: Jul | B23: =SUMPRODUCT((MONTH(Sales[Date])=7)*Sales[NetAmount]) | C23: =SUMPRODUCT((MONTH(Purchases[Date])=7)*Purchases[NetAmount]) | D23: =SUMPRODUCT((MONTH(Expenses[Date])=7)*Expenses[Amount])
A24: Aug | B24: =SUMPRODUCT((MONTH(Sales[Date])=8)*Sales[NetAmount]) | C24: =SUMPRODUCT((MONTH(Purchases[Date])=8)*Purchases[NetAmount]) | D24: =SUMPRODUCT((MONTH(Expenses[Date])=8)*Expenses[Amount])
A25: Sep | B25: =SUMPRODUCT((MONTH(Sales[Date])=9)*Sales[NetAmount]) | C25: =SUMPRODUCT((MONTH(Purchases[Date])=9)*Purchases[NetAmount]) | D25: =SUMPRODUCT((MONTH(Expenses[Date])=9)*Expenses[Amount])
A26: Oct | B26: =SUMPRODUCT((MONTH(Sales[Date])=10)*Sales[NetAmount]) | C26: =SUMPRODUCT((MONTH(Purchases[Date])=10)*Purchases[NetAmount]) | D26: =SUMPRODUCT((MONTH(Expenses[Date])=10)*Expenses[Amount])
A27: Nov | B27: =SUMPRODUCT((MONTH(Sales[Date])=11)*Sales[NetAmount]) | C27: =SUMPRODUCT((MONTH(Purchases[Date])=11)*Purchases[NetAmount]) | D27: =SUMPRODUCT((MONTH(Expenses[Date])=11)*Expenses[Amount])
A28: Dec | B28: =SUMPRODUCT((MONTH(Sales[Date])=12)*Sales[NetAmount]) | C28: =SUMPRODUCT((MONTH(Purchases[Date])=12)*Purchases[NetAmount]) | D28: =SUMPRODUCT((MONTH(Expenses[Date])=12)*Expenses[Amount])

Sheet PivotData
A1: Metric | B1: Value
A2: Total Sales | B2: =SUM(Sales[NetAmount])
A3: Total Purchases | B3: =SUM(Purchases[NetAmount])
A4: Total Expenses | B4: =SUM(Expenses[Amount])
A5: Receivables | B5: =SUM(Sales[Balance])
A6: Payables | B6: =SUM(Purchases[Balance])
A7: Inventory Value | B7: =SUM(Products[StockValue])

Sheet Settings
A1: Setting | B1: Value
A2: CompanyName | B2: Your Company
A3: Currency | B3: INR
A4: TaxRate | B4: 0
A5: Version | B5: 2.0

Sheet CustomerForm
A1: NEW CUSTOMER
A4: Enter customer details. VBA SAVE will append the record to Customers.
A6: Customer ID | B6: C002
A7: Customer Name
A8: Mobile
A9: Email
A10: Address
A11: GSTIN
A12: Opening Balance | B12: 0
A13: Credit Limit | B13: 0
A14: Status | B14: Active
A20: SAVE | C20: CLEAR

Sheet ProductForm
A1: NEW PRODUCT
A4: Enter product details. Inventory is calculated from opening stock, purchases and sales.
A6: Product ID | B6: P002
A7: Product Name
A8: Category
A9: Unit | B9: Nos
A10: Purchase Price | B10: 0
A11: Sale Price | B11: 0
A12: Opening Stock | B12: 0
A13: Reorder Level | B13: 10
A14: Status | B14: Active
A20: SAVE | C20: CLEAR

Sheet SaleForm
A1: NEW SALE
A4: Sale total, balance and payment status are calculated automatically in Sales.
A6: Sale ID | B6: S002
A7: Date | B7: 15-08-2026
A8: Customer ID | B8: C001
A9: Product ID | B9: P001
A10: Quantity | B10: 1
A11: Rate | B11: 150
A12: Discount | B12: 0
A13: Tax | B13: 0
A14: Payment Received | B14: 0
A20: SAVE | C20: CLEAR

Sheet PurchaseForm
A1: NEW PURCHASE
A4: Purchase total, supplier balance and payment status are calculated automatically.
A6: Purchase ID | B6: PUR002
A7: Date | B7: 15-08-2026
A8: Supplier ID | B8: SUP001
A9: Product ID | B9: P001
A10: Quantity | B10: 1
A11: Rate | B11: 100
A12: Tax | B12: 0
A13: Payment Made | B13: 0
A20: SAVE | C20: CLEAR

Sheet ExpenseForm
A1: NEW EXPENSE
A4: Record expenses for MIS and profit calculation.
A6: Expense ID | B6: EXP002
A7: Date | B7: 15-08-2026
A8: Category | B8: Office
A9: Description
A10: Amount | B10: 0
A11: Payment Mode | B11: Cash
A20: SAVE | C20: CLEAR

Sheet PaymentForm
A1: RECEIVE / MAKE PAYMENT
A4: Record a customer receipt or supplier payment.
A6: Payment ID | B6: PAY002
A7: Date | B7: 15-08-2026
A8: Party Type | B8: Customer
A9: Party ID | B9: C001
A10: Reference
A11: Amount | B11: 0
A12: Payment Mode | B12: Cash
A20: SAVE | C20: CLEAR

Sheet Invoice
A1: SALES INVOICE
A4: Invoice No. | B4: =SaleForm!B6 | E4: Date | F4: =SaleForm!B7
A5: Customer ID | B5: =SaleForm!B8 | E5: Customer Name | F5: =IFERROR(XLOOKUP(B5,Customers[CustomerID],Customers[CustomerName]),"")
A6: Mobile | B6: =IFERROR(XLOOKUP(B5,Customers[CustomerID],Customers[Mobile]),"")
A8: Product ID | B8: Description | C8: Qty | D8: Rate | E8: Discount | F8: Tax | G8: Net Amount
A9: =SaleForm!B9 | B9: =IFERROR(XLOOKUP(A9,Products[ProductID],Products[ProductName]),"") | C9: =SaleForm!B10 | D9: =SaleForm!B11 | E9: =SaleForm!B12 | F9: =SaleForm!B13 | G9: =C9*D9-E9+F9
F20: TOTAL | G20: =SUM(G9:G18)
A22: PDF EXPORT | D22: PRINT

Sheet Receipt
A1: PAYMENT RECEIPT
A4: Receipt No. | B4: =PaymentForm!B6
A5: Date | B5: =PaymentForm!B7
A6: Party Type | B6: =PaymentForm!B8
A7: Party ID | B7: =PaymentForm!B9
A8: Reference | B8: =PaymentForm!B10
A9: Amount | B9: =PaymentForm!B11
A10: Payment Mode | B10: =PaymentForm!B12
A13: PDF EXPORT | D13: PRINT

Sheet V3_Guide
A1: V3 BUILD GUIDE
A4: • Professional forms for Customer, Product, Sale, Purchase, Expense and Payment.
A5: • Invoice template linked to SaleForm and master data.
A6: • Receipt template linked to PaymentForm.
A7: • Print areas and page setup prepared for PDF export.
A8: • Dashboard and Data Entry navigation areas prepared.
A9: • V2 formulas, inventory, receivables, payables and KPIs remain the foundation.
A10: • Next automation stage: VBA buttons, Save/Clear, ID generation, validation, invoice PDF and receipt PDF.
